modulus/launch/__init__.py
modulus/launch/config/__init__.py
modulus/launch/logging/__init__.py
modulus/launch/logging/console.py
modulus/launch/logging/launch.py
modulus/launch/logging/mlflow.py
modulus/launch/logging/utils.py
modulus/launch/logging/wandb.py
modulus/launch/utils/__init__.py
modulus/launch/utils/checkpoint.py
nvidia_modulus.launch-0.3.1.dist-info/LICENSE.txt
nvidia_modulus.launch-0.3.1.dist-info/METADATA
nvidia_modulus.launch-0.3.1.dist-info/WHEEL
nvidia_modulus.launch-0.3.1.dist-info/top_level.txt
nvidia_modulus.launch-0.3.1.dist-info/RECORD
