Metadata-Version: 2.1
Name: nvidia-modulus.launch
Version: 0.3.1
Summary: Optimized tranining recipes for accelerating PyTorch workflows of AI driven surrogates for physical systems
Author: NVIDIA Modulus Team
License: Apache 2.0
Classifier: Programming Language :: Python :: 3
Classifier: License :: OSI Approved :: Apache Software License
Classifier: Operating System :: OS Independent
Requires-Python: >=3.8
License-File: LICENSE.txt
Requires-Dist: nvidia-modulus ==0.3.0
Requires-Dist: hydra-core >=1.2.0
Requires-Dist: termcolor >=2.1.1
Requires-Dist: wandb >=0.13.7
Requires-Dist: mlflow >=2.1.1
Requires-Dist: pytest >=6.0.0
Requires-Dist: pydantic >=1.10.2
Requires-Dist: imageio >=2.28.1
Requires-Dist: moviepy >=1.0.3
Requires-Dist: tqdm >=4.60.0
